galeshapley/__init__.py
galeshapley/base.py
galeshapley/exceptions.py
galeshapley/matchings.py
galeshapley/version.py
galeshapley/algorithms/__init__.py
galeshapley/algorithms/base_container_part.py
galeshapley/algorithms/player_allocation.py
galeshapley/algorithms/stable_duos.py
galeshapley/algorithms/stable_pairing.py
galeshapley/algorithms/util.py
galeshapley/games/__init__.py
galeshapley/games/base_container_part.py
galeshapley/games/player_allocation.py
galeshapley/games/stable_duos.py
galeshapley/games/stable_pairing.py
galeshapley/players/__init__.py
galeshapley/players/base_container.py
galeshapley/players/container.py
galeshapley/players/player.py
galeshapley/players/resource.py
galeshapley-0.1.4.dist-info/LICENSE.txt
galeshapley-0.1.4.dist-info/METADATA
galeshapley-0.1.4.dist-info/WHEEL
galeshapley-0.1.4.dist-info/top_level.txt
galeshapley-0.1.4.dist-info/RECORD
