Metadata-Version: 2.1
Name: galeshapley
Version: 0.1.4
Summary: Gale Shapley Algorithm
Home-page: https://gitlab.com/stamps-group/galeshapley
Author: Gomes, J.M.
Author-email: gomejm@ita.br
License: MIT
Keywords: game-theory gale-shapley matching-games
Platform: UNKNOWN
Requires-Python: >=3.5
License-File: LICENSE.txt
